<?xml version="1.0" encoding="UTF-8"?>
<feature
      id="sk.stuba.fiit.ProgrammerProportion.feature"
      label="Feature"
      version="1.0.0.qualifier"
      provider-name="FEROMAKOVI">

   <description url="http://www.example.com/description">
      [Enter Feature Description here.]
   </description>

   <copyright url="http://www.example.com/copyright">
      [Enter Copyright Description here.]
   </copyright>

   <license url="http://www.example.com/license">
      [Enter License Description here.]
   </license>

   <includes
         id="sk.stuba.fiit.perconik.feature"
         version="0.0.0"/>

   <requires>
      <import plugin="org.eclipse.core.runtime"/>
      <import plugin="org.eclipse.jdt.core" version="3.9.1" match="greaterOrEqual"/>
      <import plugin="org.eclipse.core.resources" version="3.8.101" match="greaterOrEqual"/>
      <import plugin="org.eclipse.core.expressions" version="3.4.500" match="greaterOrEqual"/>
      <import plugin="sk.stuba.fiit.perconik.eclipse" version="0.1.1" match="greaterOrEqual"/>
      <import plugin="sk.stuba.fiit.perconik.core.java" version="0.1.1" match="greaterOrEqual"/>
      <import plugin="com.android.ide.eclipse.base"/>
      <import plugin="org.eclipse.core.commands"/>
      <import plugin="org.eclipse.jface"/>
      <import plugin="org.eclipse.jgit"/>
      <import plugin="org.eclipse.swt"/>
      <import plugin="org.eclipse.ui.ide"/>
      <import plugin="org.eclipse.ui.workbench"/>
   </requires>

   <plugin
         id="sk.stuba.fiit.ProgrammerProportion"
         download-size="0"
         install-size="0"
         version="0.0.0"
         unpack="false"/>

</feature>
